{
	"menus": {
		"system": {
			"File": {
				"type": "menubutton",
				"text": "文件(F)...",
                "enable": true,
                "items": {
                    "New": {
                        "text": "新建文件(N)...",
						"command": "IDE.NewFile"
                    }
                }
			},
			"Sep1": "-"
		},
		"js": {
			"Cut": {
				"text": "剪切(F)..."
			}


		}


	},

	"keys": {
		"Ctrl+A": "Editor.SelectAll",
		"Ctrl+N": "IDE.NewFile",


	},

	"regions": {
		"left": {
			"panels": ["SolutionExplorer"],
			"width": 124,
			"collspaned": false
		},
		"bottom": {
			"panels": ["Find"],
			"height": 124,
			"collspaned": false
		}
	}




}